{
    "os": "Windows-10-10.0.22000-SP0",
    "python": "3.7.12",
    "heartbeatAt": "2023-08-31T08:09:07.321431",
    "startedAt": "2023-08-31T08:09:05.282977",
    "docker": null,
    "cuda": null,
    "args": [
        "--transfer_task",
        "[[1], [0]]"
    ],
    "state": "running",
    "program": "train_base.py",
    "codePath": "train_base.py",
    "git": {
        "remote": "git@github.com:Yongdream/battery.git",
        "commit": "36b43aae5c15013b6b3176b25000f454303ab32a"
    },
    "email": "youngzerooo@126.com",
    "root": "E:/Galaxy/yang7hi_battery",
    "host": "Pioneer",
    "username": "10147",
    "executable": "D:\\anaconda\\envs\\pytorch\\python.exe",
    "cpu_count": 14,
    "cpu_count_logical": 20,
    "cpu_freq": {
        "current": 2300.0,
        "min": 0.0,
        "max": 2300.0
    },
    "cpu_freq_per_core": [
        {
            "current": 2300.0,
            "min": 0.0,
            "max": 2300.0
        }
    ],
    "disk": {
        "total": 584.8681602478027,
        "used": 453.5046043395996
    },
    "gpu": "NVIDIA GeForce RTX 3060 Laptop GPU",
    "gpu_count": 1,
    "gpu_devices": [
        {
            "name": "NVIDIA GeForce RTX 3060 Laptop GPU",
            "memory_total": 6442450944
        }
    ],
    "memory": {
        "total": 15.699939727783203
    }
}
